README.md
setup.py
henry_test_tool/__init__.py
henry_test_tool/testit.py
henry_test_tool.egg-info/PKG-INFO
henry_test_tool.egg-info/SOURCES.txt
henry_test_tool.egg-info/dependency_links.txt
henry_test_tool.egg-info/top_level.txt