Metadata-Version: 1.0
Name: henry-test-tool
Version: 0.1.1
Summary: henry used for teest
Home-page: https://github.com/yunsansheng/henrytest
Author: henry.wang
Author-email: shanandone@qq.com
License: MIT Licence
Keywords: pip,henrytest,henrytool
Platform: any
